src/__init__.py
src/feature_engineering.py
formation_indus_ds_candic-0.0.1.dist-info/METADATA
formation_indus_ds_candic-0.0.1.dist-info/WHEEL
formation_indus_ds_candic-0.0.1.dist-info/top_level.txt
formation_indus_ds_candic-0.0.1.dist-info/RECORD
