Metadata-Version: 2.1
Name: formation-indus-ds-candic
Version: 0.0.1
Summary: hello
Home-page: UNKNOWN
Author: c.fraisse
Author-email: 
License: UNKNOWN
Platform: UNKNOWN
Requires-Dist: numpy (==1.23.4)
Requires-Dist: pandas (==1.5.0)
Requires-Dist: setuptools (==60.2.0)
